ezbeq/VERSION
ezbeq/__init__.py
ezbeq/apis/__init__.py
ezbeq/apis/audiotypes.py
ezbeq/apis/authors.py
ezbeq/apis/catalogue.py
ezbeq/apis/contenttypes.py
ezbeq/apis/devices.py
ezbeq/apis/diagnostics.py
ezbeq/apis/languages.py
ezbeq/apis/load.py
ezbeq/apis/meta.py
ezbeq/apis/search.py
ezbeq/apis/version.py
ezbeq/apis/ws.py
ezbeq/apis/years.py
ezbeq/camilladsp.py
ezbeq/catalogue.py
ezbeq/config.py
ezbeq/device.py
ezbeq/htp1.py
ezbeq/iir.py
ezbeq/jriver.py
ezbeq/main.py
ezbeq/minidsp.py
ezbeq/qsys.py
ezbeq/ui/android-chrome-192x192.png
ezbeq/ui/android-chrome-512x512.png
ezbeq/ui/apple-touch-icon.png
ezbeq/ui/assets/index-B2KeyMkn.js
ezbeq/ui/assets/index-DCoUB2Lx.css
ezbeq/ui/assets/roboto-cyrillic-400-normal-C5q4FMUG.woff
ezbeq/ui/assets/roboto-cyrillic-400-normal-DAIM1_dR.woff2
ezbeq/ui/assets/roboto-cyrillic-ext-400-normal-5IDvadIC.woff
ezbeq/ui/assets/roboto-cyrillic-ext-400-normal-DzMWdK87.woff2
ezbeq/ui/assets/roboto-greek-400-normal-DwVopRQH.woff
ezbeq/ui/assets/roboto-greek-400-normal-jFM2czAU.woff2
ezbeq/ui/assets/roboto-latin-400-normal-BX2H0A0_.woff
ezbeq/ui/assets/roboto-latin-400-normal-CNwBRw8h.woff2
ezbeq/ui/assets/roboto-latin-ext-400-normal-BG57dRWO.woff
ezbeq/ui/assets/roboto-latin-ext-400-normal-ZYmyxeOy.woff2
ezbeq/ui/assets/roboto-math-400-normal-B3wgz80t.woff2
ezbeq/ui/assets/roboto-math-400-normal-BRMeFL5Z.woff
ezbeq/ui/assets/roboto-symbols-400-normal-B2LMqLB2.woff
ezbeq/ui/assets/roboto-symbols-400-normal-fF1SLJBj.woff2
ezbeq/ui/assets/roboto-vietnamese-400-normal-BYP5tVVv.woff
ezbeq/ui/assets/roboto-vietnamese-400-normal-CDDxGrUb.woff2
ezbeq/ui/browserconfig.xml
ezbeq/ui/favicon-16x16.png
ezbeq/ui/favicon-32x32.png
ezbeq/ui/favicon.ico
ezbeq/ui/index.html
ezbeq/ui/mstile-150x150.png
ezbeq/ui/robots.txt
ezbeq/ui/safari-pinned-tab.svg
ezbeq/ui/site.webmanifest
ezbeq-2.4.0.dist-info/LICENSE
ezbeq-2.4.0.dist-info/METADATA
ezbeq-2.4.0.dist-info/WHEEL
ezbeq-2.4.0.dist-info/entry_points.txt
ezbeq-2.4.0.dist-info/RECORD
