Metadata-Version: 2.3
Name: ezbeq
Version: 2.4.0
Summary: A webapp which can send beqcatalogue filters to a DSP device
License: MIT
Author: 3ll3d00d
Author-email: mattkhan+ezbeq@gmail.com
Requires-Python: >=3.11, <3.14
Classifier: License :: OSI Approved :: MIT License
Classifier: Programming Language :: Python :: 3
Classifier: Programming Language :: Python :: 3.11
Classifier: Programming Language :: Python :: 3.12
Classifier: Programming Language :: Python :: 3.13
Requires-Dist: Flask-Compress (>=1.13,<2.0)
Requires-Dist: PyYAML (>=6.0,<7.0)
Requires-Dist: Twisted (>=24.3.0,<26.0)
Requires-Dist: autobahn[twisted] (>=24.4.2,<25.0)
Requires-Dist: flask-restx (>=1.3.0,<2.0)
Requires-Dist: ijson (>=3.2.3,<4.0)
Requires-Dist: plumbum (>=1.8.1,<2.0)
Requires-Dist: prometheus-client (>=0.17.1,<1.0)
Requires-Dist: psutil (>=5.9.5,<6.0)
Requires-Dist: python-dateutil (>=2.8.2,<3.0)
Requires-Dist: requests (>=2.30.0,<3.0)
Requires-Dist: semver (>=3.0.0,<4.0)
